ibuk_dl/__init__.py
ibuk_dl/main.py
ibuk_dl/yeast.py
ibuk_dl-0.2.dist-info/LICENSE
ibuk_dl-0.2.dist-info/METADATA
ibuk_dl-0.2.dist-info/WHEEL
ibuk_dl-0.2.dist-info/entry_points.txt
ibuk_dl-0.2.dist-info/top_level.txt
ibuk_dl-0.2.dist-info/RECORD
