Metadata-Version: 2.1
Name: ibuk-dl
Version: 0.2
Summary: Download books from libra.ibuk.pl
Author-email: Ignacy Sewastianowicz <szpiren@gmail.com>
Project-URL: Homepage, https://github.com/ignassew/ibuk-dl
Classifier: Programming Language :: Python :: 3
Classifier: License :: OSI Approved :: MIT License
Classifier: Operating System :: OS Independent
Classifier: Intended Audience :: End Users/Desktop
License-File: LICENSE
Requires-Dist: beautifulsoup4
Requires-Dist: requests
Requires-Dist: websockets
